beetsplug/__init__.py
beetsplug/restapi.py
beets_rest_api-0.2.3.dist-info/LICENSE
beets_rest_api-0.2.3.dist-info/METADATA
beets_rest_api-0.2.3.dist-info/WHEEL
beets_rest_api-0.2.3.dist-info/top_level.txt
beets_rest_api-0.2.3.dist-info/RECORD
