Metadata-Version: 2.1
Name: beets-rest-api
Version: 0.2.3
Summary: beets plugin that provides a basic REST api
Home-page: https://github.com/calne-ca/beets-plugin-restapi
Author: Joscha Düringer
Author-email: joscha.dueringer@beardbot.net
License: MIT
Platform: ALL
Classifier: Topic :: Multimedia :: Sound/Audio
Classifier: Topic :: Multimedia :: Sound/Audio :: Players :: MP3
Classifier: License :: OSI Approved :: MIT License
Classifier: Environment :: Console
Classifier: Programming Language :: Python :: 3
Classifier: Programming Language :: Python :: 3.4
Classifier: Programming Language :: Python :: 3.5
Classifier: Programming Language :: Python :: 3.6
Classifier: Programming Language :: Python :: 3.7
Requires-Dist: beets (>=1.4.7)
Requires-Dist: mediafile (>=0.9.0)
Requires-Dist: pillow (>=8.3.2)
Requires-Dist: flask
